datasette_debug_actors_from_ids.py
datasette_debug_actors_from_ids-0.1a3.dist-info/licenses/LICENSE
datasette_debug_actors_from_ids-0.1a3.dist-info/METADATA
datasette_debug_actors_from_ids-0.1a3.dist-info/WHEEL
datasette_debug_actors_from_ids-0.1a3.dist-info/entry_points.txt
datasette_debug_actors_from_ids-0.1a3.dist-info/top_level.txt
datasette_debug_actors_from_ids-0.1a3.dist-info/RECORD
