Metadata-Version: 2.4
Name: datasette-debug-actors-from-ids
Version: 0.1a3
Summary: Datasette plugin for trying out the actors_from_ids hook
Author: Simon Willison
License-Expression: Apache-2.0
Project-URL: Homepage, https://github.com/datasette/datasette-debug-actors-from-ids
Project-URL: Changelog, https://github.com/datasette/datasette-debug-actors-from-ids/releases
Project-URL: Issues, https://github.com/datasette/datasette-debug-actors-from-ids/issues
Project-URL: CI, https://github.com/datasette/datasette-debug-actors-from-ids/actions
Classifier: Framework :: Datasette
License-File: LICENSE
Requires-Dist: datasette>=1.0a21
Provides-Extra: test
Requires-Dist: pytest; extra == "test"
Requires-Dist: pytest-httpx; extra == "test"
Requires-Dist: pytest-asyncio; extra == "test"
Dynamic: license-file
